README.md
setup.py
lib/joo/LICENSE
lib/joo/__init__.py
lib/joo/__version__.py
lib/joo/cli.py
lib/joo/datetimeutil.py
lib/joo/httpapi.py
lib/joo/logging.py
lib/joo/sysutil.py
lib/joo.egg-info/PKG-INFO
lib/joo.egg-info/SOURCES.txt
lib/joo.egg-info/dependency_links.txt
lib/joo.egg-info/top_level.txt
lib/joo/db/__init__.py
lib/joo/db/mysql.py
lib/joo/db/pep249.py
lib/joo/db/sqlbuilder.py
lib/joo/db/sqlite.py
lib/joo/scraping/__init__.py
lib/joo/scraping/http.py
lib/joo/scraping/selenium.py